TeXid/__init__.py
TeXid/configuration.py
TeXid/dataloader.py
TeXid/model.py
TeXid/pl_wrapper.py
TeXid/postprocess.py
TeXid/tokenizer.py
TeXid-0.1.3.dist-info/METADATA
TeXid-0.1.3.dist-info/WHEEL
TeXid-0.1.3.dist-info/top_level.txt
TeXid-0.1.3.dist-info/RECORD
