Metadata-Version: 2.1
Name: TeXid
Version: 0.1.3
Summary: Tense Identification using HuggingFace RoBERTa
Author: Le Minh Khoi
License: MIT
Classifier: Programming Language :: Python :: 3
Classifier: License :: OSI Approved :: MIT License
Classifier: Operating System :: OS Independent
Requires-Python: >=3.8
